yaad/__init__.py
yaad/attr_dict.py
yaad/py.typed
yaad-1.1.1.dist-info/WHEEL
yaad-1.1.1.dist-info/METADATA
yaad-1.1.1.dist-info/RECORD
